keboola_python/__init__.py
keboola_python/base_component.py
keboola_python-0.1.3.dist-info/licenses/LICENSE
keboola_python-0.1.3.dist-info/METADATA
keboola_python-0.1.3.dist-info/WHEEL
keboola_python-0.1.3.dist-info/top_level.txt
keboola_python-0.1.3.dist-info/RECORD
