Metadata-Version: 2.4
Name: keboola-python
Version: 0.1.3
Summary: Common base classes for Keboola Python components
Author-email: George Millard <george.millard@ellenmacarthurfoundation.org>
License: MIT
Project-URL: Homepage, https://github.com/emfoundation/keboola-python
Project-URL: Repository, https://github.com/emfoundation/keboola-python
Requires-Python: >=3.10
License-File: LICENSE
Dynamic: license-file
